<?xml version="1.0" encoding="UTF-8" ?>
<!-- *************************************************************************************
FILE DESCRIPTION
Max Top 5 critical clocks will be reported. For rest user needs to refer to Detailed report
*******************************************************************************************-->
<report_table display_priority="2" name="Timing Summary">
<report_link name="Detailed report">
<data>X:\Graduate\ECEN5863\ProgrammableLogic\Homework6\Question2\fifo2x8\synthesis\synlog\fifo2x8_fpga_mapper.srr</data>
<title>START OF TIMING REPORT</title>
</report_link>
<row>
<data tcl_name="clock_name">Clock Name</data>
<data tcl_name="req_freq">Req Freq</data>
<data tcl_name="est_freq">Est Freq</data>
<data tcl_name="slack">Slack</data>
</row>
<row>
<data>fifo2x8|clk1</data>
<data>100.0 MHz</data>
<data>422.9 MHz</data>
<data>7.635</data>
</row>
<row>
<data>fifo2x8|clk2</data>
<data>100.0 MHz</data>
<data>515.5 MHz</data>
<data>8.060</data>
</row>
</report_table>
